Workbook

Sheet Dashboard
A1: OORU LOGIX — YEAR 1 FINANCIAL DASHBOARD
A3: Total Revenue (12 months) | B3: =Revenue!B14
A4: Total Gross Profit | B4: =P&L!B14
A5: Gross Margin % | B5: =P&L!C14
A6: EBITDA (12 months) | B6: =P&L!E14
A7: Closing Cash Balance | B7: =CashFlow!G14
A8: Units Sold (ShopSense) | B8: =Revenue!D14
A9: Web Design Deals Closed | B9: =Revenue!E14
A10: Monthly CAC | B10: =Assumptions!B7
A13: SCENARIO COMPARISON | B13: Conservative | C13: Base Case | D13: Optimistic
A14: Year 1 Revenue | B14: =Scenarios!B3 | C14: =Scenarios!C3 | D14: =Scenarios!D3
A15: Total Units | B15: =Scenarios!B5 | C15: =Scenarios!C5 | D15: =Scenarios!D5
A16: Year 1 EBITDA | B16: =Scenarios!B7 | C16: =Scenarios!C7 | D16: =Scenarios!D7

Sheet Assumptions
A1: ASSUMPTIONS & INPUT PARAMETERS
A3: ShopSense Unit Price (₹) | B3: 25000
A4: ShopSense COGS (₹) | B4: 13750
A5: Gross Margin % (ShopSense) | B5: 0.45
A6: Web Design Avg Deal (₹) | B6: 8000
A7: CAC per Customer (₹) | B7: 0
A8: Monthly OpEx (₹) | B8: 10500
A9: GST Rate % | B9: 0.18
A10: Starting Cash (₹) | B10: 50000
A12: MONTHLY UNIT RAMP (ShopSense units)
A13: Month | B13: M1 | C13: M2 | D13: M3 | E13: M4 | F13: M5 | G13: M6 | H13: M7 | I13: M8 | J13: M9 | K13: M10 | L13: M11 | M13: M12
A14: Units | B14: 0 | C14: 0 | D14: 0 | E14: 1 | F14: 1 | G14: 2 | H14: 2 | I14: 3 | J14: 3 | K14: 4 | L14: 5 | M14: 5
A17: MONTHLY WEB DESIGN DEALS
A18: Month | B18: M1 | C18: M2 | D18: M3 | E18: M4 | F18: M5 | G18: M6 | H18: M7 | I18: M8 | J18: M9 | K18: M10 | L18: M11 | M18: M12
A19: Deals | B19: 0 | C19: 0 | D19: 1 | E19: 1 | F19: 2 | G19: 2 | H19: 2 | I19: 3 | J19: 3 | K19: 3 | L19: 4 | M19: 4

Sheet Revenue
A1: MONTHLY REVENUE ANALYSIS | B1: Month 1 | C1: Month 2 | D1: Month 3 | E1: Month 4 | F1: Month 5 | G1: Month 6 | H1: Month 7 | I1: Month 8 | J1: Month 9 | K1: Month 10 | L1: Month 11 | M1: Month 12 | N1: Year 1 Total
A2: ShopSense Units Sold | B2: =Assumptions!B18 | C2: =Assumptions!C18 | D2: =Assumptions!D18 | E2: =Assumptions!E18 | F2: =Assumptions!F18 | G2: =Assumptions!G18 | H2: =Assumptions!H18 | I2: =Assumptions!I18 | ... M2: =Assumptions!M18 | N2: =SUM(B2:M2)
A3: ShopSense Revenue (₹) | B3: =B2*Assumptions!B1 | C3: =B2*Assumptions!B1 | D3: =B2*Assumptions!B1 | E3: =B2*Assumptions!B1 | F3: =B2*Assumptions!B1 | G3: =B2*Assumptions!B1 | H3: =B2*Assumptions!B1 | I3: =B2*Assumptions!B1 | J3: =B2*Assumptions!B1 | K3: =B2*Assumptions!B1 | L3: =B2*Assumptions!B1 | M3: =B2*Assumptions!B1 | N3: =SUM(B3:M3)
A4: Web Design Deals | B4: =Assumptions!B23 | C4: =Assumptions!C23 | D4: =Assumptions!D23 | E4: =Assumptions!E23 | F4: =Assumptions!F23 | G4: =Assumptions!G23 | H4: =Assumptions!H23 | I4: =Assumptions!I23 | ... M4: =Assumptions!M23 | N4: =SUM(B4:M4)
A5: Web Design Revenue (₹) | B5: =B4*Assumptions!B4 | C5: =B4*Assumptions!B4 | D5: =B4*Assumptions!B4 | E5: =B4*Assumptions!B4 | F5: =B4*Assumptions!B4 | G5: =B4*Assumptions!B4 | H5: =B4*Assumptions!B4 | I5: =B4*Assumptions!B4 | J5: =B4*Assumptions!B4 | K5: =B4*Assumptions!B4 | L5: =B4*Assumptions!B4 | M5: =B4*Assumptions!B4 | N5: =SUM(B5:M5)
A6: TOTAL REVENUE (₹) | B6: =B4+B2 | C6: =B4+B2 | D6: =B4+B2 | E6: =B4+B2 | F6: =B4+B2 | G6: =B4+B2 | H6: =B4+B2 | I6: =B4+B2 | J6: =B4+B2 | K6: =B4+B2 | L6: =B4+B2 | M6: =B4+B2 | N6: =SUM(B6:M6)
A7: Cumulative Revenue (₹) | B7: =B6 | C7: =B6+B6 | D7: =C6+B6 | E7: =D6+B6 | F7: =E6+B6 | G7: =F6+B6 | H7: =G6+B6 | I7: =H6+B6 | J7: =I6+B6 | K7: =J6+B6 | L7: =K6+B6 | M7: =L6+B6

Sheet P&L
A1: PROFIT & LOSS STATEMENT | B1: Month 1 | C1: Month 2 | D1: Month 3 | E1: Month 4 | F1: Month 5 | G1: Month 6 | H1: Month 7 | I1: Month 8 | J1: Month 9 | K1: Month 10 | L1: Month 11 | M1: Month 12 | N1: Year 1 Total
A2: Revenue | B2: =Revenue!B6:B6 | C2: =Revenue!B6:C6 | D2: =Revenue!B6:D6 | E2: =Revenue!B6:E6 | F2: =Revenue!B6:F6 | G2: =Revenue!B6:G6 | H2: =Revenue!B6:H6 | I2: =Revenue!B6:I6 | J2: =Revenue!B6:J6 | K2: =Revenue!B6:K6 | L2: =Revenue!B6:L6 | M2: =Revenue!B6:M6 | N2: =Revenue!N5
A3: COGS (ShopSense only) | B3: =Revenue!B3*Assumptions!B2 | C3: =Revenue!B3*Assumptions!B2 | D3: =Revenue!B3*Assumptions!B2 | E3: =Revenue!B3*Assumptions!B2 | F3: =Revenue!B3*Assumptions!B2 | G3: =Revenue!B3*Assumptions!B2 | H3: =Revenue!B3*Assumptions!B2 | I3: =Revenue!B3*Assumptions!B2 | J3: =Revenue!B3*Assumptions!B2 | K3: =Revenue!B3*Assumptions!B2 | L3: =Revenue!B3*Assumptions!B2 | M3: =Revenue!B3*Assumptions!B2 | N3: =SUM(B3:M3)
A4: Gross Profit (₹) | B4: =B2-B3 | C4: =B2-B3 | D4: =B2-B3 | E4: =B2-B3 | F4: =B2-B3 | G4: =B2-B3 | H4: =B2-B3 | I4: =B2-B3 | J4: =B2-B3 | K4: =B2-B3 | L4: =B2-B3 | M4: =B2-B3 | N4: =SUM(B4:M4)
A5: Gross Margin % | B5: =IF(B2=0,0,B4/B2) | C5: =IF(B2=0,0,B4/B2) | D5: =IF(B2=0,0,B4/B2) | E5: =IF(B2=0,0,B4/B2) | F5: =IF(B2=0,0,B4/B2) | G5: =IF(B2=0,0,B4/B2) | H5: =IF(B2=0,0,B4/B2) | I5: =IF(B2=0,0,B4/B2) | J5: =IF(B2=0,0,B4/B2) | K5: =IF(B2=0,0,B4/B2) | L5: =IF(B2=0,0,B4/B2) | M5: =IF(B2=0,0,B4/B2) | N5: =IF(N2=0,0,N4/N2)
A7: Operating Expenses | B7: =Assumptions!B6 | C7: =Assumptions!B6 | D7: =Assumptions!B6 | E7: =Assumptions!B6 | F7: =Assumptions!B6 | G7: =Assumptions!B6 | H7: =Assumptions!B6 | I7: =Assumptions!B6 | J7: =Assumptions!B6 | K7: =Assumptions!B6 | L7: =Assumptions!B6 | M7: =Assumptions!B6 | N7: =SUM(B7:M7)
A8: EBITDA (₹) | B8: =B4-B7 | C8: =B4-B7 | D8: =B4-B7 | E8: =B4-B7 | F8: =B4-B7 | G8: =B4-B7 | H8: =B4-B7 | I8: =B4-B7 | J8: =B4-B7 | K8: =B4-B7 | L8: =B4-B7 | M8: =B4-B7 | N8: =SUM(B8:M8)

Sheet CashFlow
A1: MONTHLY CASH FLOW STATEMENT | B1: Month 1 | C1: Month 2 | D1: Month 3 | E1: Month 4 | F1: Month 5 | G1: Month 6 | H1: Month 7 | I1: Month 8 | J1: Month 9 | K1: Month 10 | L1: Month 11 | M1: Month 12 | N1: Year 1 Total
A2: Opening Cash Balance (₹) | B2: =Assumptions!B8 | C2: =C10 | D2: =D10 | E2: =E10 | F2: =F10 | G2: =G10 | H2: =H10 | I2: =I10 | J2: =J10 | ... M2: =M10
A3: Cash In (Revenue) | B3: =Revenue!B6 | C3: =Revenue!B6 | D3: =Revenue!B6 | E3: =Revenue!B6 | F3: =Revenue!B6 | G3: =Revenue!B6 | H3: =Revenue!B6 | I3: =Revenue!B6 | J3: =Revenue!B6 | K3: =Revenue!B6 | L3: =Revenue!B6 | M3: =Revenue!B6 | N3: =SUM(B3:M3)
A4: Cash Out: COGS (2 weeks prior) | B4: =Revenue!B3*Assumptions!B2 | C4: =B3*Assumptions!B2 | D4: =C3*Assumptions!B2 | E4: =D3*Assumptions!B2 | F4: =E3*Assumptions!B2 | G4: =F3*Assumptions!B2 | H4: =G3*Assumptions!B2 | I4: =H3*Assumptions!B2 | J4: =I3*Assumptions!B2 | K4: =J3*Assumptions!B2 | L4: =K3*Assumptions!B2 | M4: =L3*Assumptions!B2 | N4: =SUM(B4:M4)
A5: Cash Out: Operating Expenses | B5: =Assumptions!B6 | C5: =Assumptions!B6 | D5: =Assumptions!B6 | E5: =Assumptions!B6 | F5: =Assumptions!B6 | G5: =Assumptions!B6 | H5: =Assumptions!B6 | I5: =Assumptions!B6 | J5: =Assumptions!B6 | K5: =Assumptions!B6 | L5: =Assumptions!B6 | M5: =Assumptions!B6 | N5: =SUM(B5:M5)
A6: Total Cash Out | B6: =B4+B5 | C6: =B4+B5 | D6: =B4+B5 | E6: =B4+B5 | F6: =B4+B5 | G6: =B4+B5 | H6: =B4+B5 | I6: =B4+B5 | J6: =B4+B5 | K6: =B4+B5 | L6: =B4+B5 | M6: =B4+B5 | N6: =SUM(B6:M6)
A7: Net Cash Flow (₹) | B7: =B3-B6 | C7: =B3-B6 | D7: =B3-B6 | E7: =B3-B6 | F7: =B3-B6 | G7: =B3-B6 | H7: =B3-B6 | I7: =B3-B6 | J7: =B3-B6 | K7: =B3-B6 | L7: =B3-B6 | M7: =B3-B6 | N7: =SUM(B7:M7)
A8: Closing Cash Balance (₹) | B8: =B1+B7 | C8: =C1+B7 | D8: =D1+B7 | E8: =E1+B7 | F8: =F1+B7 | G8: =G1+B7 | H8: =H1+B7 | I8: =I1+B7 | J8: =J1+B7 | K8: =K1+B7 | L8: =L1+B7 | M8: =M1+B7 | N8: =M8

Sheet UnitEconomics
A1: PER-UNIT ECONOMICS (ShopSense)
A3: Unit Price (₹) | B3: =Assumptions!B1
A4: COGS (₹) | B4: =Assumptions!B2
A5: Gross Profit per Unit (₹) | B5: =B2-B3
A6: Gross Margin % | B6: =B4/B2
A9: CUSTOMER LIFETIME VALUE (CLV) ANALYSIS
A10: Year 1 Hardware Sale (₹) | B10: =Assumptions!B1
A11: Year 1 Service Revenue (₹) | B11: 5000
A12: Year 1 Upgrade Potential (₹) | B12: 2000
A13: Total LTV Year 1 (₹) | B13: =B8+B9+B10
A15: Customer Acquisition Cost (CAC) | B15: =Assumptions!B5
A16: LTV / CAC Ratio | B16: =IF(B15=0,999,B14/B15)
A18: Payback Period Calculation
A19: Monthly Savings per Shop (₹) | B19: 8333
A20: Payback Period (months) | B20: =ROUNDUP(Assumptions!B1/B19, 0)

Sheet Scenarios
A1: SCENARIO ANALYSIS | B1: Conservative | C1: Base Case | D1: Optimistic
A2: Unit Multiplier | B2: 1 | C2: 1.5 | D2: 2.5
A3: Year 1 Revenue (₹) | B3: =Revenue!N5 | C3: =Revenue!N5*C2 | D3: =Revenue!N5*D2
A4: Total Units Sold | B4: =Revenue!N3 | C4: =Revenue!N3*C2 | D4: =Revenue!N3*D2
A5: Year 1 EBITDA (₹) | B5: =P&L!N5 | C5: =P&L!N2*C2-P&L!N4*(C2-1) | D5: =P&L!N2*D2-P&L!N4*(D2-1)
